<?xml version="1.0" encoding="UTF-8" ?>
<utilidades.CentralDeInformacoes>
  <programas>
    <modelo.programa.SeriesRegulares>
      <id>1659053311893</id>
      <nome>eaeee</nome>
      <tipo>SERIES_REGULARES</tipo>
      <canal class="modelo.canal.CanalBroadcasting">
        <nome>lasead</nome>
        <tipoCanal>ASSINATURA_INDIVIDUAL_DE_BROADCASTING</tipoCanal>
        <id>1659051943805</id>
        <programas/>
        <dataDeCadastro>2022-07-28T20:45:43.8086677</dataDeCadastro>
        <dataDeAtualizacao>2022-07-29T01:39:48.720602</dataDeAtualizacao>
        <dono>
          <nome>manco</nome>
          <email>manco@gmail.com</email>
          <login>manco</login>
          <senha>Mancones1</senha>
          <confirmacaoDeSenha>Mancones1</confirmacaoDeSenha>
          <programasFavoritos/>
        </dono>
        <link>las.com</link>
      </canal>
      <status>EXIBICAO</status>
      <favorito>FAVORITO</favorito>
      <horario>22:22</horario>
      <temporadas>004</temporadas>
      <diasDaSemana>
        <day-of-week>MONDAY</day-of-week>
        <day-of-week>TUESDAY</day-of-week>
        <day-of-week>THURSDAY</day-of-week>
        <day-of-week>FRIDAY</day-of-week>
        <day-of-week>SATURDAY</day-of-week>
        <day-of-week>SUNDAY</day-of-week>
      </diasDaSemana>
      <genero>COMEDIA</genero>
      <estilo>LIVE_ACTION</estilo>
    </modelo.programa.SeriesRegulares>
    <modelo.programa.SeriesRegulares>
      <id>1659053312792</id>
      <nome>eaeee</nome>
      <tipo>SERIES_REGULARES</tipo>
      <canal class="modelo.canal.CanalBroadcasting" reference="../../modelo.programa.SeriesRegulares/canal"/>
      <status>EXIBICAO</status>
      <favorito>FAVORITO</favorito>
      <horario>22:22</horario>
      <temporadas>004</temporadas>
      <diasDaSemana reference="../../modelo.programa.SeriesRegulares/diasDaSemana"/>
      <genero>COMEDIA</genero>
      <estilo>LIVE_ACTION</estilo>
    </modelo.programa.SeriesRegulares>
    <modelo.programa.SeriesRegulares>
      <id>1659053313247</id>
      <nome>eaeee</nome>
      <tipo>SERIES_REGULARES</tipo>
      <canal class="modelo.canal.CanalBroadcasting" reference="../../modelo.programa.SeriesRegulares/canal"/>
      <status>EXIBICAO</status>
      <favorito>FAVORITO</favorito>
      <horario>22:22</horario>
      <temporadas>004</temporadas>
      <diasDaSemana reference="../../modelo.programa.SeriesRegulares/diasDaSemana"/>
      <genero>COMEDIA</genero>
      <estilo>LIVE_ACTION</estilo>
    </modelo.programa.SeriesRegulares>
    <modelo.programa.SeriesRegulares>
      <id>1659053313646</id>
      <nome>eaeee</nome>
      <tipo>SERIES_REGULARES</tipo>
      <canal class="modelo.canal.CanalBroadcasting" reference="../../modelo.programa.SeriesRegulares/canal"/>
      <status>EXIBICAO</status>
      <favorito>FAVORITO</favorito>
      <horario>22:22</horario>
      <temporadas>004</temporadas>
      <diasDaSemana reference="../../modelo.programa.SeriesRegulares/diasDaSemana"/>
      <genero>COMEDIA</genero>
      <estilo>LIVE_ACTION</estilo>
    </modelo.programa.SeriesRegulares>
  </programas>
  <canais>
    <modelo.canal.CanalBroadcasting reference="../../programas/modelo.programa.SeriesRegulares/canal"/>
    <modelo.canal.CanalBroadcasting>
      <nome>mamac</nome>
      <tipoCanal>ABERTO_NA_INTERNET_BROADCASTING</tipoCanal>
      <id>1659051965027</id>
      <programas/>
      <dataDeCadastro>2022-07-28T20:46:05.0273028</dataDeCadastro>
      <dono>
        <nome>manco</nome>
        <email>manco@gmail.com</email>
        <login>manco</login>
        <senha>Mancones1</senha>
        <confirmacaoDeSenha>Mancones1</confirmacaoDeSenha>
        <programasFavoritos/>
      </dono>
      <link>ca.ocm</link>
    </modelo.canal.CanalBroadcasting>
    <modelo.canal.CanalDeTv>
      <nome>orango</nome>
      <tipoCanal>CANAL_ABERTO_DE_TELEVISAO</tipoCanal>
      <id>1659068253959</id>
      <programas/>
      <dataDeCadastro>2022-07-29T01:17:33.9596856</dataDeCadastro>
      <dono>
        <nome>manco</nome>
        <email>manco@gmail.com</email>
        <login>manco</login>
        <senha>Mancones1</senha>
        <confirmacaoDeSenha>Mancones1</confirmacaoDeSenha>
        <programasFavoritos/>
      </dono>
      <numeroCanal>23</numeroCanal>
    </modelo.canal.CanalDeTv>
  </canais>
  <usuariosCadastrados>
    <modelo.usuario.Usuario>
      <nome>dsadasd</nome>
      <email>abcds@gmail.com</email>
      <login>Abcd1234</login>
      <senha>Abcd1234</senha>
      <confirmacaoDeSenha>Abcd1234</confirmacaoDeSenha>
      <programasFavoritos/>
    </modelo.usuario.Usuario>
  </usuariosCadastrados>
</utilidades.CentralDeInformacoes>